{
  "precipitation_annual_mm": {
    "2012": 2845.8,
    "2013": 2985.1,
    "2014": 2826.4,
    "2015": 2704.7,
    "2016": 2706.2,
    "2017": 2944.4,
    "2018": 2944.5,
    "2019": 2738.6,
    "2020": 2821.6,
    "2021": 2973.4,
    "2022": 3464.0,
    "2023": 2597.2,
    "2024": 2725.5
  },
  "lst_annual_C": {
    "2012": 27.93,
    "2013": 27.72,
    "2014": 28.09,
    "2015": 28.65,
    "2016": 28.36,
    "2017": 27.85,
    "2018": 27.97,
    "2019": 28.24,
    "2020": 28.21,
    "2021": 27.8,
    "2022": 27.01,
    "2023": 27.78,
    "2024": 27.69
  },
  "trends": {
    "precipitation": {
      "kendall_tau": -0.0513,
      "p_value": 0.857734,
      "sen_slope_mm_yr": -2.04,
      "significant": "False"
    },
    "lst": {
      "kendall_tau": -0.3333,
      "p_value": 0.128851,
      "sen_slope_C_yr": -0.0371,
      "significant": "False"
    }
  },
  "spi_2013": {
    "SPI_mean": -0.1427892387692282,
    "SPI_stdDev": 0.5276928555663889
  },
  "spi_2016": {
    "SPI_mean": -0.8557589772393279,
    "SPI_stdDev": 0.6308546499546273
  },
  "spi_2020": {
    "SPI_mean": -0.48371575455595156,
    "SPI_stdDev": 0.8011059339647604
  },
  "spi_2024": {
    "SPI_mean": -0.889155983220198,
    "SPI_stdDev": 0.8886357733465533
  },
  "drought_frequency": {
    "drought_frequency_max": 0.6923076923076923,
    "drought_frequency_mean": 0.2628825512164419
  }
}